nsfds3/__init__.py
nsfds3/main.py
nsfds3/cpgrid/__init__.py
nsfds3/cpgrid/cdomain.py
nsfds3/cpgrid/cutils.c
nsfds3/cpgrid/cutils.cpython-311-darwin.so
nsfds3/cpgrid/cutils.pyx
nsfds3/cpgrid/geometry.py
nsfds3/cpgrid/gridutils.c
nsfds3/cpgrid/gridutils.cpython-311-darwin.so
nsfds3/cpgrid/gridutils.pyx
nsfds3/cpgrid/mesh.py
nsfds3/cpgrid/templates.py
nsfds3/cpgrid/utils.py
nsfds3/graphics/__init__.py
nsfds3/graphics/graphics.py
nsfds3/graphics/utils.py
nsfds3/materials/__init__.py
nsfds3/materials/gas.py
nsfds3/solver/__init__.py
nsfds3/solver/config.py
nsfds3/solver/fdtd.py
nsfds3/solver/sources.py
nsfds3/utils/__init__.py
nsfds3/utils/data.py
nsfds3/utils/fdutils.py
nsfds3/utils/files.py
nsfds3/utils/headers.py
nsfds3/utils/misc.py
nsfds3-1.0.0.dist-info/LICENSE
nsfds3-1.0.0.dist-info/METADATA
nsfds3-1.0.0.dist-info/WHEEL
nsfds3-1.0.0.dist-info/entry_points.txt
nsfds3-1.0.0.dist-info/top_level.txt
nsfds3-1.0.0.dist-info/RECORD
