Metadata-Version: 2.1
Name: nsfds3
Version: 1.0.0
Summary: Finite difference solver for Navier-Stokes equations
Author-email: Cyril Desjouy <cyril.desjouy@univ-lemans.fr>
License: GNU GENERAL PUBLIC LICENSE
Project-URL: Homepage, https://github.com/ipselium/nsfds3
Project-URL: Documentation, https://perso.univ-lemans.fr/~cdesjouy/nsfds3
Classifier: Programming Language :: Python :: 3.11
Classifier: License :: OSI Approved :: GNU General Public License v3 or later (GPLv3+)
Classifier: Operating System :: OS Independent
Classifier: Development Status :: 4 - Beta
Classifier: Intended Audience :: Science/Research
Classifier: Topic :: Scientific/Engineering :: Physics
Classifier: Topic :: Software Development :: Libraries :: Python Modules
Requires-Python: >=3.11
License-File: LICENSE
Requires-Dist: numpy >=1.26.0
Requires-Dist: scipy
Requires-Dist: matplotlib >=3.9.0
Requires-Dist: plotly
Requires-Dist: rich
Requires-Dist: h5py
